.coveragerc
.editorconfig
.gitignore
.travis.yml
AUTHORS.rst
CONTRIBUTING.rst
HISTORY.rst
LICENSE
MANIFEST.in
Makefile
README.rst
manage.py
requirements.txt
requirements_dev.txt
requirements_test.txt
runtests.py
setup.cfg
setup.py
tox.ini
.github/ISSUE_TEMPLATE.md
.github/workflows/main.yml
django_next_url_mixin.egg-info/PKG-INFO
django_next_url_mixin.egg-info/SOURCES.txt
django_next_url_mixin.egg-info/dependency_links.txt
django_next_url_mixin.egg-info/not-zip-safe
django_next_url_mixin.egg-info/top_level.txt
docs/Makefile
docs/authors.rst
docs/conf.py
docs/contributing.rst
docs/history.rst
docs/index.rst
docs/installation.rst
docs/make.bat
docs/modules.rst
docs/next_url_mixin.rst
docs/readme.rst
docs/usage.rst
next_url_mixin/__init__.py
next_url_mixin/mixin.py
tests/README.md
tests/__init__.py
tests/requirements.txt
tests/settings.py
tests/test_views.py
tests/urls.py